ZetcodePythonJiaochengChuyi/README.md
ZetcodePythonJiaochengChuyi/__init__.py
ZetcodePythonJiaochengChuyi/__main__.py
ZetcodePythonJiaochengChuyi/file.epub
ZetcodePythonJiaochengChuyi/index.html
ZetcodePythonJiaochengChuyi/css/__init__.py
ZetcodePythonJiaochengChuyi/css/annotations.css
ZetcodePythonJiaochengChuyi/css/main.css
ZetcodePythonJiaochengChuyi/css/normalize.css
ZetcodePythonJiaochengChuyi/css/popup.css
ZetcodePythonJiaochengChuyi/font/__init__.py
ZetcodePythonJiaochengChuyi/font/fontello.eot
ZetcodePythonJiaochengChuyi/font/fontello.svg
ZetcodePythonJiaochengChuyi/font/fontello.ttf
ZetcodePythonJiaochengChuyi/font/fontello.woff
ZetcodePythonJiaochengChuyi/img/__init__.py
ZetcodePythonJiaochengChuyi/img/annotator-glyph-sprite.png
ZetcodePythonJiaochengChuyi/img/annotator-icon-sprite.png
ZetcodePythonJiaochengChuyi/img/apple-touch-icon.png
ZetcodePythonJiaochengChuyi/img/cancelfullscreen.png
ZetcodePythonJiaochengChuyi/img/close.png
ZetcodePythonJiaochengChuyi/img/fullscreen.png
ZetcodePythonJiaochengChuyi/img/loader.gif
ZetcodePythonJiaochengChuyi/img/menu-icon.png
ZetcodePythonJiaochengChuyi/img/save.png
ZetcodePythonJiaochengChuyi/img/saved.png
ZetcodePythonJiaochengChuyi/img/settings-s.png
ZetcodePythonJiaochengChuyi/img/settings.png
ZetcodePythonJiaochengChuyi/img/star.png
ZetcodePythonJiaochengChuyi/js/__init__.py
ZetcodePythonJiaochengChuyi/js/epub.js
ZetcodePythonJiaochengChuyi/js/epub.min.js
ZetcodePythonJiaochengChuyi/js/epub.min.map
ZetcodePythonJiaochengChuyi/js/hooks.min.js
ZetcodePythonJiaochengChuyi/js/hooks.min.map
ZetcodePythonJiaochengChuyi/js/reader.js
ZetcodePythonJiaochengChuyi/js/reader.js.map
ZetcodePythonJiaochengChuyi/js/reader.min.js
ZetcodePythonJiaochengChuyi/js/reader.min.map
ZetcodePythonJiaochengChuyi/js/hooks/__init__.py
ZetcodePythonJiaochengChuyi/js/hooks/extensions/__init__.py
ZetcodePythonJiaochengChuyi/js/hooks/extensions/highlight.js
ZetcodePythonJiaochengChuyi/js/libs/__init__.py
zetcode_python_jiaocheng_chuyi-2024.3.5.0.dist-info/METADATA
zetcode_python_jiaocheng_chuyi-2024.3.5.0.dist-info/WHEEL
zetcode_python_jiaocheng_chuyi-2024.3.5.0.dist-info/entry_points.txt
zetcode_python_jiaocheng_chuyi-2024.3.5.0.dist-info/top_level.txt
zetcode_python_jiaocheng_chuyi-2024.3.5.0.dist-info/RECORD
